odoo/addons/delivery_postlogistics_server_env/README.rst
odoo/addons/delivery_postlogistics_server_env/__init__.py
odoo/addons/delivery_postlogistics_server_env/__manifest__.py
odoo/addons/delivery_postlogistics_server_env/i18n/delivery_postlogistics_server_env.pot
odoo/addons/delivery_postlogistics_server_env/i18n/es.po
odoo/addons/delivery_postlogistics_server_env/i18n/it.po
odoo/addons/delivery_postlogistics_server_env/i18n/pt_BR.po
odoo/addons/delivery_postlogistics_server_env/models/__init__.py
odoo/addons/delivery_postlogistics_server_env/models/delivery_carrier.py
odoo/addons/delivery_postlogistics_server_env/readme/CONTRIBUTORS.md
odoo/addons/delivery_postlogistics_server_env/readme/CREDITS.md
odoo/addons/delivery_postlogistics_server_env/readme/DESCRIPTION.md
odoo/addons/delivery_postlogistics_server_env/static/description/icon.png
odoo/addons/delivery_postlogistics_server_env/static/description/index.html
odoo/addons/delivery_postlogistics_server_env/tests/__init__.py
odoo/addons/delivery_postlogistics_server_env/tests/test_delivery_postlogistics_server_env.py
odoo_addon_delivery_postlogistics_server_env-18.0.1.0.0.3.dist-info/METADATA
odoo_addon_delivery_postlogistics_server_env-18.0.1.0.0.3.dist-info/WHEEL
odoo_addon_delivery_postlogistics_server_env-18.0.1.0.0.3.dist-info/top_level.txt
odoo_addon_delivery_postlogistics_server_env-18.0.1.0.0.3.dist-info/RECORD
